hx711/__init__.py
hx711-1.1.2.3.dist-info/METADATA
hx711-1.1.2.3.dist-info/RECORD
hx711-1.1.2.3.dist-info/WHEEL
hx711-1.1.2.3.dist-info/top_level.txt
