Metadata-Version: 2.1
Name: hx711
Version: 1.1.2.3
Summary: A library to drive a HX711 load cell amplifier on a Raspberry Pi
Home-page: https://github.com/mpibpc-mroose/hx711/
Author: Marco Roose
Author-email: marco.roose@gmx.de
License: MIT license
Project-URL: Bug Reports, https://github.com/mpibpc-mroose/hx711/issues
Keywords: hx711
Platform: UNKNOWN
Classifier: Intended Audience :: Developers
Classifier: License :: OSI Approved :: MIT License
Classifier: Natural Language :: English
Classifier: Programming Language :: Python :: 3.5
